{
  "data": {
    "article": {},
    "attachments": {},
    "author_id": "1779063322500874240",
    "conversation_id": "1939973226693616108",
    "created_at": "2025-07-03T07:42:33.000Z",
    "edit_controls": {
      "editable_until": "2025-07-03T08:42:33.000Z",
      "edits_remaining": 5,
      "is_edit_eligible": false
    },
    "edit_history_tweet_ids": [
      "1940677527909146868"
    ],
    "entities": {
      "mentions": [
        {
          "end": 12,
          "id": "1784234307428737024",
          "start": 0,
          "username": "xiaoyu_iren"
        }
      ]
    },
    "geo": {},
    "id": "1940677527909146868",
    "in_reply_to_user_id": "1784234307428737024",
    "lang": "zh",
    "note_tweet": {
      "entities": {}
    },
    "possibly_sensitive": false,
    "public_metrics": {
      "bookmark_count": 0,
      "impression_count": 0,
      "like_count": 0,
      "quote_count": 0,
      "reply_count": 0,
      "retweet_count": 0
    },
    "referenced_tweets": [
      {
        "id": "1939973226693616108",
        "type": "replied_to"
      }
    ],
    "reply_settings": "everyone",
    "text": "@xiaoyu_iren 四爱"
  },
  "includes": {
    "tweets": [
      {
        "article": {},
        "attachments": {},
        "author_id": "1779063322500874240",
        "conversation_id": "1939973226693616108",
        "created_at": "2025-07-03T07:42:33.000Z",
        "edit_controls": {
          "editable_until": "2025-07-03T08:42:33.000Z",
          "edits_remaining": 5,
          "is_edit_eligible": false
        },
        "edit_history_tweet_ids": [
          "1940677527909146868"
        ],
        "entities": {
          "mentions": [
            {
              "end": 12,
              "id": "1784234307428737024",
              "start": 0,
              "username": "xiaoyu_iren"
            }
          ]
        },
        "geo": {},
        "id": "1940677527909146868",
        "in_reply_to_user_id": "1784234307428737024",
        "lang": "zh",
        "note_tweet": {
          "entities": {}
        },
        "possibly_sensitive": false,
        "public_metrics": {
          "bookmark_count": 0,
          "impression_count": 0,
          "like_count": 0,
          "quote_count": 0,
          "reply_count": 0,
          "retweet_count": 0
        },
        "referenced_tweets": [
          {
            "id": "1939973226693616108",
            "type": "replied_to"
          }
        ],
        "reply_settings": "everyone",
        "text": "@xiaoyu_iren 四爱"
      },
      {
        "article": {},
        "attachments": {},
        "author_id": "1784234307428737024",
        "conversation_id": "1939973226693616108",
        "created_at": "2025-07-01T09:03:54.000Z",
        "edit_controls": {
          "editable_until": "2025-07-01T10:03:54.000Z",
          "edits_remaining": 5,
          "is_edit_eligible": true
        },
        "edit_history_tweet_ids": [
          "1939973226693616108"
        ],
        "entities": {},
        "geo": {},
        "id": "1939973226693616108",
        "lang": "zh",
        "note_tweet": {
          "entities": {}
        },
        "possibly_sensitive": false,
        "public_metrics": {
          "bookmark_count": 36,
          "impression_count": 85289,
          "like_count": 378,
          "quote_count": 0,
          "reply_count": 16,
          "retweet_count": 8
        },
        "reply_settings": "everyone",
        "text": "刚给男朋友量了一下鸡鸡。吃完药后完全勃起，8cm。小小的好可爱，哈哈哈哈。虽然给不了我高潮了，但是他爱我就好，我也不需要他给我高潮"
      }
    ],
    "users": [
      {
        "created_at": "2024-04-13T08:25:35.000Z",
        "description": "20080627\n主推路飞/索隆/波奇酱/乌萨奇/小八/库洛米/香克斯 爱哭的笨蛋  敏感抑郁焦虑 善良🥺🤗成分复杂 抽象",
        "id": "1779063322500874240",
        "name": "困困鱼崽仔小云🥰👿🥺🤗😡😡",
        "pinned_tweet_id": "1914559190288453846",
        "profile_image_url": "https://pbs.twimg.com/profile_images/1907334411152158720/pPb-PHRW_normal.jpg",
        "protected": false,
        "public_metrics": {
          "followers_count": 235,
          "following_count": 1266,
          "like_count": 19230,
          "listed_count": 0,
          "media_count": 90,
          "tweet_count": 1070
        },
        "username": "kunkunyuzaizai",
        "verified": false
      },
      {
        "created_at": "2024-04-27T14:53:22.000Z",
        "description": "和男朋友是真爱，别怀疑\n求关注\n\n男朋友拍的照片都在下面链接，链接的私信必回",
        "entities": {
          "url": {
            "urls": [
              {
                "display_url": "afans.vip/xiaoyu_iren",
                "end": 23,
                "expanded_url": "https://afans.vip/xiaoyu_iren",
                "start": 0,
                "url": "https://t.co/Ikc2dGGyKN"
              }
            ]
          }
        },
        "id": "1784234307428737024",
        "name": "小雨Iren",
        "pinned_tweet_id": "1794692200745558023",
        "profile_image_url": "https://pbs.twimg.com/profile_images/1784235187318173696/HK2HwQkT_normal.jpg",
        "protected": false,
        "public_metrics": {
          "followers_count": 34849,
          "following_count": 6,
          "like_count": 8,
          "listed_count": 49,
          "media_count": 10,
          "tweet_count": 451
        },
        "url": "https://t.co/Ikc2dGGyKN",
        "username": "xiaoyu_iren",
        "verified": false
      }
    ]
  }
}