{
  "data": {
    "article": {},
    "attachments": {},
    "author_id": "1779063322500874240",
    "conversation_id": "1950241940001476936",
    "created_at": "2025-07-30T04:24:26.000Z",
    "edit_controls": {
      "editable_until": "2025-07-30T05:24:26.000Z",
      "edits_remaining": 5,
      "is_edit_eligible": false
    },
    "edit_history_tweet_ids": [
      "1950412144367030295"
    ],
    "entities": {
      "mentions": [
        {
          "end": 16,
          "id": "1898223080100737024",
          "start": 0,
          "username": "daoooollll33611"
        }
      ]
    },
    "geo": {},
    "id": "1950412144367030295",
    "in_reply_to_user_id": "1898223080100737024",
    "lang": "zh",
    "note_tweet": {
      "entities": {}
    },
    "possibly_sensitive": false,
    "public_metrics": {
      "bookmark_count": 0,
      "impression_count": 0,
      "like_count": 0,
      "quote_count": 0,
      "reply_count": 0,
      "retweet_count": 0
    },
    "referenced_tweets": [
      {
        "id": "1950241940001476936",
        "type": "replied_to"
      }
    ],
    "reply_settings": "everyone",
    "text": "@daoooollll33611 我168cm 体重43-45.5kg之间变化 08年的🌚"
  },
  "includes": {
    "tweets": [
      {
        "article": {},
        "attachments": {},
        "author_id": "1779063322500874240",
        "conversation_id": "1950241940001476936",
        "created_at": "2025-07-30T04:24:26.000Z",
        "edit_controls": {
          "editable_until": "2025-07-30T05:24:26.000Z",
          "edits_remaining": 5,
          "is_edit_eligible": false
        },
        "edit_history_tweet_ids": [
          "1950412144367030295"
        ],
        "entities": {
          "mentions": [
            {
              "end": 16,
              "id": "1898223080100737024",
              "start": 0,
              "username": "daoooollll33611"
            }
          ]
        },
        "geo": {},
        "id": "1950412144367030295",
        "in_reply_to_user_id": "1898223080100737024",
        "lang": "zh",
        "note_tweet": {
          "entities": {}
        },
        "possibly_sensitive": false,
        "public_metrics": {
          "bookmark_count": 0,
          "impression_count": 0,
          "like_count": 0,
          "quote_count": 0,
          "reply_count": 0,
          "retweet_count": 0
        },
        "referenced_tweets": [
          {
            "id": "1950241940001476936",
            "type": "replied_to"
          }
        ],
        "reply_settings": "everyone",
        "text": "@daoooollll33611 我168cm 体重43-45.5kg之间变化 08年的🌚"
      },
      {
        "article": {},
        "attachments": {},
        "author_id": "1898223080100737024",
        "conversation_id": "1950241940001476936",
        "created_at": "2025-07-29T17:08:06.000Z",
        "edit_controls": {
          "editable_until": "2025-07-29T18:08:06.000Z",
          "edits_remaining": 5,
          "is_edit_eligible": true
        },
        "edit_history_tweet_ids": [
          "1950241940001476936"
        ],
        "entities": {},
        "geo": {},
        "id": "1950241940001476936",
        "lang": "zh",
        "note_tweet": {
          "entities": {}
        },
        "possibly_sensitive": false,
        "public_metrics": {
          "bookmark_count": 0,
          "impression_count": 16,
          "like_count": 0,
          "quote_count": 0,
          "reply_count": 0,
          "retweet_count": 0
        },
        "reply_settings": "everyone",
        "text": "如果18岁男生168身高正常吗，现在才42kg，我想问我以后能干啥😭👎"
      }
    ],
    "users": [
      {
        "created_at": "2024-04-13T08:25:35.000Z",
        "description": "20080627\n主推路飞/索隆/波奇酱/乌萨奇/小八/库洛米/香克斯 爱哭的笨蛋  敏感抑郁焦虑 善良🥺🤗成分复杂 抽象",
        "id": "1779063322500874240",
        "name": "困困鱼崽仔小云🥰👿🥺🤗😡😡",
        "pinned_tweet_id": "1914559190288453846",
        "profile_image_url": "https://pbs.twimg.com/profile_images/1907334411152158720/pPb-PHRW_normal.jpg",
        "protected": false,
        "public_metrics": {
          "followers_count": 250,
          "following_count": 1298,
          "like_count": 20069,
          "listed_count": 0,
          "media_count": 94,
          "tweet_count": 1147
        },
        "username": "kunkunyuzaizai",
        "verified": false
      },
      {
        "created_at": "2025-03-08T04:03:53.000Z",
        "description": "",
        "id": "1898223080100737024",
        "name": "daoooolllliii",
        "profile_image_url": "https://pbs.twimg.com/profile_images/1947340141955321856/QIAyzXOF_normal.jpg",
        "protected": false,
        "public_metrics": {
          "followers_count": 15,
          "following_count": 40,
          "like_count": 108,
          "listed_count": 0,
          "media_count": 5,
          "tweet_count": 107
        },
        "username": "daoooollll33611",
        "verified": false
      }
    ]
  }
}