{
  "data": {
    "article": {},
    "attachments": {},
    "author_id": "1779063322500874240",
    "conversation_id": "1996931893036831195",
    "created_at": "2025-12-06T04:44:46.000Z",
    "edit_controls": {
      "editable_until": "2025-12-06T05:44:46.000Z",
      "edits_remaining": 5,
      "is_edit_eligible": false
    },
    "edit_history_tweet_ids": [
      "1997165294251540673"
    ],
    "entities": {
      "mentions": [
        {
          "end": 13,
          "id": "1924851439576481796",
          "start": 0,
          "username": "meowmi071207"
        },
        {
          "end": 23,
          "id": "1513898402366439427",
          "start": 14,
          "username": "QvQ_1111"
        }
      ]
    },
    "geo": {},
    "id": "1997165294251540673",
    "in_reply_to_user_id": "1924851439576481796",
    "lang": "zh",
    "note_tweet": {
      "entities": {}
    },
    "possibly_sensitive": false,
    "public_metrics": {
      "bookmark_count": 0,
      "impression_count": 0,
      "like_count": 0,
      "quote_count": 0,
      "reply_count": 0,
      "retweet_count": 0
    },
    "referenced_tweets": [
      {
        "id": "1996979464056738023",
        "type": "replied_to"
      }
    ],
    "reply_settings": "everyone",
    "text": "@meowmi071207 @QvQ_1111 缺爱就不会爱自己了"
  },
  "includes": {
    "tweets": [
      {
        "article": {},
        "attachments": {},
        "author_id": "1779063322500874240",
        "conversation_id": "1996931893036831195",
        "created_at": "2025-12-06T04:44:46.000Z",
        "edit_controls": {
          "editable_until": "2025-12-06T05:44:46.000Z",
          "edits_remaining": 5,
          "is_edit_eligible": false
        },
        "edit_history_tweet_ids": [
          "1997165294251540673"
        ],
        "entities": {
          "mentions": [
            {
              "end": 13,
              "id": "1924851439576481796",
              "start": 0,
              "username": "meowmi071207"
            },
            {
              "end": 23,
              "id": "1513898402366439427",
              "start": 14,
              "username": "QvQ_1111"
            }
          ]
        },
        "geo": {},
        "id": "1997165294251540673",
        "in_reply_to_user_id": "1924851439576481796",
        "lang": "zh",
        "note_tweet": {
          "entities": {}
        },
        "possibly_sensitive": false,
        "public_metrics": {
          "bookmark_count": 0,
          "impression_count": 0,
          "like_count": 0,
          "quote_count": 0,
          "reply_count": 0,
          "retweet_count": 0
        },
        "referenced_tweets": [
          {
            "id": "1996979464056738023",
            "type": "replied_to"
          }
        ],
        "reply_settings": "everyone",
        "text": "@meowmi071207 @QvQ_1111 缺爱就不会爱自己了"
      },
      {
        "article": {},
        "attachments": {},
        "author_id": "1924851439576481796",
        "conversation_id": "1996931893036831195",
        "created_at": "2025-12-05T16:26:20.000Z",
        "edit_controls": {
          "editable_until": "2025-12-05T17:26:20.000Z",
          "edits_remaining": 5,
          "is_edit_eligible": false
        },
        "edit_history_tweet_ids": [
          "1996979464056738023"
        ],
        "entities": {
          "mentions": [
            {
              "end": 9,
              "id": "1513898402366439427",
              "start": 0,
              "username": "QvQ_1111"
            }
          ]
        },
        "geo": {},
        "id": "1996979464056738023",
        "in_reply_to_user_id": "1513898402366439427",
        "lang": "zh",
        "note_tweet": {
          "entities": {}
        },
        "possibly_sensitive": false,
        "public_metrics": {
          "bookmark_count": 0,
          "impression_count": 462,
          "like_count": 2,
          "quote_count": 0,
          "reply_count": 2,
          "retweet_count": 0
        },
        "referenced_tweets": [
          {
            "id": "1996931893036831195",
            "type": "replied_to"
          }
        ],
        "reply_settings": "everyone",
        "text": "@QvQ_1111 我感觉有部分人可能没有那么自爱。"
      }
    ],
    "users": [
      {
        "created_at": "2024-04-13T08:25:35.000Z",
        "description": "20080627 INFP 巨蟹男\n168CM/50KG\nXNN\n叫我小云就好了🥰\nDREAM IS BE A GIRL\n\n匿名提问https://t.co/3xGifEjlmO",
        "entities": {
          "description": {
            "urls": [
              {
                "display_url": "ngl.link/kunkunyu627",
                "end": 89,
                "expanded_url": "https://ngl.link/kunkunyu627",
                "start": 66,
                "url": "https://t.co/3xGifEjlmO"
              }
            ]
          }
        },
        "id": "1779063322500874240",
        "name": "困困鱼崽仔小云",
        "pinned_tweet_id": "1961203265527283808",
        "profile_image_url": "https://pbs.twimg.com/profile_images/1907334411152158720/pPb-PHRW_normal.jpg",
        "protected": false,
        "public_metrics": {
          "followers_count": 471,
          "following_count": 2358,
          "like_count": 33952,
          "listed_count": 0,
          "media_count": 149,
          "tweet_count": 2478
        },
        "username": "kunkunyuzaizai",
        "verified": false
      },
      {
        "created_at": "2025-05-20T15:35:33.000Z",
        "description": "😢",
        "id": "1924851439576481796",
        "name": "meowmi",
        "profile_image_url": "https://pbs.twimg.com/profile_images/1924852941430915072/qPVmCS8M_normal.jpg",
        "protected": false,
        "public_metrics": {
          "followers_count": 17,
          "following_count": 1,
          "like_count": 210,
          "listed_count": 1,
          "media_count": 19,
          "tweet_count": 193
        },
        "username": "meowmi071207",
        "verified": false
      },
      {
        "created_at": "2022-04-12T15:14:50.000Z",
        "description": "我很脆弱。我一定还会回来的！不聊不约别发来恶心我😷匿名问答：https://t.co/02AmJFCDEU",
        "entities": {
          "description": {
            "urls": [
              {
                "display_url": "ngl.link/amaya_ovo",
                "end": 53,
                "expanded_url": "https://ngl.link/amaya_ovo",
                "start": 30,
                "url": "https://t.co/02AmJFCDEU"
              }
            ]
          }
        },
        "id": "1513898402366439427",
        "location": "抱抱",
        "name": "烦烦",
        "pinned_tweet_id": "1989400290320421039",
        "profile_image_url": "https://pbs.twimg.com/profile_images/1986441853252870144/k8sqxodJ_normal.jpg",
        "protected": false,
        "public_metrics": {
          "followers_count": 808,
          "following_count": 297,
          "like_count": 3214,
          "listed_count": 4,
          "media_count": 198,
          "tweet_count": 2062
        },
        "username": "QvQ_1111",
        "verified": false
      }
    ]
  }
}