{
  "data": {
    "article": {},
    "attachments": {},
    "author_id": "1779063322500874240",
    "conversation_id": "1969272982011830578",
    "created_at": "2025-09-20T05:30:40.000Z",
    "edit_controls": {
      "editable_until": "2025-09-20T06:30:40.000Z",
      "edits_remaining": 5,
      "is_edit_eligible": true
    },
    "edit_history_tweet_ids": [
      "1969272982011830578"
    ],
    "entities": {
      "urls": [
        {
          "display_url": "ngl.link/kunkunyu627",
          "end": 31,
          "expanded_url": "https://ngl.link/kunkunyu627",
          "start": 8,
          "status": 200,
          "unwound_url": "https://ngl.link/kunkunyu627",
          "url": "https://t.co/FLZTFfhuQF"
        }
      ]
    },
    "geo": {},
    "id": "1969272982011830578",
    "lang": "zh",
    "note_tweet": {
      "entities": {}
    },
    "possibly_sensitive": true,
    "public_metrics": {
      "bookmark_count": 0,
      "impression_count": 0,
      "like_count": 0,
      "quote_count": 0,
      "reply_count": 0,
      "retweet_count": 0
    },
    "reply_settings": "everyone",
    "text": "给我发送匿名消息https://t.co/FLZTFfhuQF"
  },
  "includes": {
    "tweets": [
      {
        "article": {},
        "attachments": {},
        "author_id": "1779063322500874240",
        "conversation_id": "1969272982011830578",
        "created_at": "2025-09-20T05:30:40.000Z",
        "edit_controls": {
          "editable_until": "2025-09-20T06:30:40.000Z",
          "edits_remaining": 5,
          "is_edit_eligible": true
        },
        "edit_history_tweet_ids": [
          "1969272982011830578"
        ],
        "entities": {
          "urls": [
            {
              "display_url": "ngl.link/kunkunyu627",
              "end": 31,
              "expanded_url": "https://ngl.link/kunkunyu627",
              "start": 8,
              "status": 200,
              "unwound_url": "https://ngl.link/kunkunyu627",
              "url": "https://t.co/FLZTFfhuQF"
            }
          ]
        },
        "geo": {},
        "id": "1969272982011830578",
        "lang": "zh",
        "note_tweet": {
          "entities": {}
        },
        "possibly_sensitive": true,
        "public_metrics": {
          "bookmark_count": 0,
          "impression_count": 0,
          "like_count": 0,
          "quote_count": 0,
          "reply_count": 0,
          "retweet_count": 0
        },
        "reply_settings": "everyone",
        "text": "给我发送匿名消息https://t.co/FLZTFfhuQF"
      }
    ],
    "users": [
      {
        "created_at": "2024-04-13T08:25:35.000Z",
        "description": "20080627 INFP 巨蟹 \n男生哦 2i＆4i\n担ROSE＆LISA",
        "id": "1779063322500874240",
        "name": "困困鱼崽仔小云🥰👿🥺🤗😡😡",
        "pinned_tweet_id": "1961203265527283808",
        "profile_image_url": "https://pbs.twimg.com/profile_images/1907334411152158720/pPb-PHRW_normal.jpg",
        "protected": false,
        "public_metrics": {
          "followers_count": 402,
          "following_count": 1976,
          "like_count": 29563,
          "listed_count": 0,
          "media_count": 125,
          "tweet_count": 2043
        },
        "username": "kunkunyuzaizai",
        "verified": false
      }
    ]
  }
}