{
  "data": {
    "article": {},
    "attachments": {},
    "author_id": "1779063322500874240",
    "conversation_id": "2004595066862784642",
    "created_at": "2025-12-27T07:10:41.000Z",
    "edit_controls": {
      "editable_until": "2025-12-27T08:10:41.000Z",
      "edits_remaining": 5,
      "is_edit_eligible": false
    },
    "edit_history_tweet_ids": [
      "2004812159520551140"
    ],
    "entities": {
      "mentions": [
        {
          "end": 16,
          "id": "1983420652981010432",
          "start": 0,
          "username": "dissolvingspace"
        }
      ]
    },
    "geo": {},
    "id": "2004812159520551140",
    "in_reply_to_user_id": "1983420652981010432",
    "lang": "zh",
    "note_tweet": {
      "entities": {}
    },
    "possibly_sensitive": false,
    "public_metrics": {
      "bookmark_count": 0,
      "impression_count": 0,
      "like_count": 0,
      "quote_count": 0,
      "reply_count": 0,
      "retweet_count": 0
    },
    "referenced_tweets": [
      {
        "id": "2004595066862784642",
        "type": "replied_to"
      }
    ],
    "reply_settings": "everyone",
    "text": "@dissolvingspace 大学毕业嘛"
  },
  "includes": {
    "tweets": [
      {
        "article": {},
        "attachments": {},
        "author_id": "1779063322500874240",
        "conversation_id": "2004595066862784642",
        "created_at": "2025-12-27T07:10:41.000Z",
        "edit_controls": {
          "editable_until": "2025-12-27T08:10:41.000Z",
          "edits_remaining": 5,
          "is_edit_eligible": false
        },
        "edit_history_tweet_ids": [
          "2004812159520551140"
        ],
        "entities": {
          "mentions": [
            {
              "end": 16,
              "id": "1983420652981010432",
              "start": 0,
              "username": "dissolvingspace"
            }
          ]
        },
        "geo": {},
        "id": "2004812159520551140",
        "in_reply_to_user_id": "1983420652981010432",
        "lang": "zh",
        "note_tweet": {
          "entities": {}
        },
        "possibly_sensitive": false,
        "public_metrics": {
          "bookmark_count": 0,
          "impression_count": 0,
          "like_count": 0,
          "quote_count": 0,
          "reply_count": 0,
          "retweet_count": 0
        },
        "referenced_tweets": [
          {
            "id": "2004595066862784642",
            "type": "replied_to"
          }
        ],
        "reply_settings": "everyone",
        "text": "@dissolvingspace 大学毕业嘛"
      },
      {
        "article": {},
        "attachments": {},
        "author_id": "1983420652981010432",
        "conversation_id": "2004595066862784642",
        "created_at": "2025-12-26T16:48:02.000Z",
        "edit_controls": {
          "editable_until": "2025-12-26T17:48:02.000Z",
          "edits_remaining": 5,
          "is_edit_eligible": true
        },
        "edit_history_tweet_ids": [
          "2004595066862784642"
        ],
        "entities": {
          "urls": [
            {
              "display_url": "x.com/qqqqqf5/status…",
              "end": 77,
              "expanded_url": "https://twitter.com/qqqqqf5/status/2004592906313892033",
              "start": 54,
              "url": "https://t.co/6i75IL1W2j"
            }
          ]
        },
        "geo": {},
        "id": "2004595066862784642",
        "lang": "zh",
        "note_tweet": {
          "entities": {}
        },
        "possibly_sensitive": false,
        "public_metrics": {
          "bookmark_count": 0,
          "impression_count": 428,
          "like_count": 13,
          "quote_count": 0,
          "reply_count": 2,
          "retweet_count": 0
        },
        "referenced_tweets": [
          {
            "id": "2004592906313892033",
            "type": "quoted"
          }
        ],
        "reply_settings": "everyone",
        "text": "我肯定要活到30岁！我要顺利拿到毕业证、以女性身份恋爱、争取和家人达成妥协……未来要做的事还有很多很多呢！ https://t.co/6i75IL1W2j"
      }
    ],
    "users": [
      {
        "created_at": "2024-04-13T08:25:35.000Z",
        "description": "20080627 INFP 巨蟹男\n168CM/50KG\nXNN\n叫我小云就好了🥰\nDREAM IS BE A GIRL\n\n匿名提问https://t.co/3xGifEiNxg",
        "entities": {
          "description": {
            "urls": [
              {
                "display_url": "ngl.link/kunkunyu627",
                "end": 89,
                "expanded_url": "https://ngl.link/kunkunyu627",
                "start": 66,
                "url": "https://t.co/3xGifEiNxg"
              }
            ]
          }
        },
        "id": "1779063322500874240",
        "name": "困困鱼崽仔小云",
        "pinned_tweet_id": "1961203265527283808",
        "profile_image_url": "https://pbs.twimg.com/profile_images/1907334411152158720/pPb-PHRW_normal.jpg",
        "protected": false,
        "public_metrics": {
          "followers_count": 512,
          "following_count": 2396,
          "like_count": 36518,
          "listed_count": 0,
          "media_count": 150,
          "tweet_count": 2576
        },
        "username": "kunkunyuzaizai",
        "verified": false
      },
      {
        "created_at": "2025-10-29T06:29:01.000Z",
        "description": "🏳️‍⚧️🍥00年大龄MTF（HRT 始于2025.10）丨🟣INTP  丨📍原籍山东，现常居武汉 ✨欢迎互fo、同城面基～",
        "id": "1983420652981010432",
        "location": "武汉市",
        "name": "小溶🏳️‍⚧️🍥",
        "pinned_tweet_id": "2003335516155252774",
        "profile_image_url": "https://pbs.twimg.com/profile_images/2001162086848847873/PbkAI_vQ_normal.jpg",
        "protected": false,
        "public_metrics": {
          "followers_count": 311,
          "following_count": 199,
          "like_count": 214,
          "listed_count": 0,
          "media_count": 63,
          "tweet_count": 475
        },
        "username": "dissolvingspace",
        "verified": false
      }
    ]
  }
}