{
  "data": {
    "article": {},
    "attachments": {},
    "author_id": "1779063322500874240",
    "conversation_id": "1898915715111092242",
    "created_at": "2025-03-16T04:56:09.000Z",
    "edit_controls": {
      "editable_until": "2025-03-16T05:56:09.000Z",
      "edits_remaining": 5,
      "is_edit_eligible": false
    },
    "edit_history_tweet_ids": [
      "1901135375474598374"
    ],
    "entities": {
      "mentions": [
        {
          "end": 7,
          "id": "1851133158374457345",
          "start": 0,
          "username": "lhy146"
        }
      ]
    },
    "geo": {},
    "id": "1901135375474598374",
    "in_reply_to_user_id": "1851133158374457345",
    "lang": "zh",
    "note_tweet": {
      "entities": {}
    },
    "possibly_sensitive": false,
    "public_metrics": {
      "bookmark_count": 0,
      "impression_count": 0,
      "like_count": 0,
      "quote_count": 0,
      "reply_count": 0,
      "retweet_count": 0
    },
    "referenced_tweets": [
      {
        "id": "1898915715111092242",
        "type": "replied_to"
      }
    ],
    "reply_settings": "everyone",
    "text": "@lhy146 这是在哪"
  },
  "includes": {
    "media": [
      {
        "duration_ms": 117666,
        "height": 960,
        "media_key": "7_1898915634718834688",
        "preview_image_url": "https://pbs.twimg.com/ext_tw_video_thumb/1898915634718834688/pu/img/IKfxtWMm35GNaEbz.jpg",
        "public_metrics": {
          "view_count": 19828
        },
        "type": "video",
        "variants": [
          {
            "bit_rate": 632000,
            "content_type": "video/mp4",
            "url": "https://video.twimg.com/ext_tw_video/1898915634718834688/pu/vid/avc1/320x426/UxdHaxyITLNc1FPe.mp4?tag=12"
          },
          {
            "bit_rate": 950000,
            "content_type": "video/mp4",
            "url": "https://video.twimg.com/ext_tw_video/1898915634718834688/pu/vid/avc1/480x640/SWu-HPZlvkeUSdpS.mp4?tag=12"
          },
          {
            "bit_rate": 2176000,
            "content_type": "video/mp4",
            "url": "https://video.twimg.com/ext_tw_video/1898915634718834688/pu/vid/avc1/720x960/_AM9862cNgbk-fD7.mp4?tag=12"
          },
          {
            "content_type": "application/x-mpegURL",
            "url": "https://video.twimg.com/ext_tw_video/1898915634718834688/pu/pl/wvCEYFZ2nGyeoH-H.m3u8?tag=12"
          }
        ],
        "width": 720
      }
    ],
    "tweets": [
      {
        "article": {},
        "attachments": {},
        "author_id": "1779063322500874240",
        "conversation_id": "1898915715111092242",
        "created_at": "2025-03-16T04:56:09.000Z",
        "edit_controls": {
          "editable_until": "2025-03-16T05:56:09.000Z",
          "edits_remaining": 5,
          "is_edit_eligible": false
        },
        "edit_history_tweet_ids": [
          "1901135375474598374"
        ],
        "entities": {
          "mentions": [
            {
              "end": 7,
              "id": "1851133158374457345",
              "start": 0,
              "username": "lhy146"
            }
          ]
        },
        "geo": {},
        "id": "1901135375474598374",
        "in_reply_to_user_id": "1851133158374457345",
        "lang": "zh",
        "note_tweet": {
          "entities": {}
        },
        "possibly_sensitive": false,
        "public_metrics": {
          "bookmark_count": 0,
          "impression_count": 0,
          "like_count": 0,
          "quote_count": 0,
          "reply_count": 0,
          "retweet_count": 0
        },
        "referenced_tweets": [
          {
            "id": "1898915715111092242",
            "type": "replied_to"
          }
        ],
        "reply_settings": "everyone",
        "text": "@lhy146 这是在哪"
      },
      {
        "article": {},
        "attachments": {
          "media_keys": [
            "7_1898915634718834688"
          ]
        },
        "author_id": "1851133158374457345",
        "conversation_id": "1898915715111092242",
        "created_at": "2025-03-10T01:56:01.000Z",
        "edit_controls": {
          "editable_until": "2025-03-10T02:56:01.000Z",
          "edits_remaining": 5,
          "is_edit_eligible": true
        },
        "edit_history_tweet_ids": [
          "1898915715111092242"
        ],
        "entities": {
          "hashtags": [
            {
              "end": 32,
              "start": 29,
              "tag": "男娘"
            },
            {
              "end": 36,
              "start": 33,
              "tag": "伪娘"
            },
            {
              "end": 44,
              "start": 37,
              "tag": "女装・男の娘"
            },
            {
              "end": 48,
              "start": 45,
              "tag": "萝莉"
            }
          ],
          "urls": [
            {
              "display_url": "pic.x.com/YEIKldjFMU",
              "end": 72,
              "expanded_url": "https://x.com/lhy146/status/1898915715111092242/video/1",
              "media_key": "7_1898915634718834688",
              "start": 49,
              "url": "https://t.co/YEIKldjFMU"
            }
          ]
        },
        "geo": {},
        "id": "1898915715111092242",
        "lang": "zh",
        "note_tweet": {
          "entities": {}
        },
        "possibly_sensitive": true,
        "public_metrics": {
          "bookmark_count": 267,
          "impression_count": 66261,
          "like_count": 1063,
          "quote_count": 0,
          "reply_count": 12,
          "retweet_count": 113
        },
        "reply_settings": "everyone",
        "text": "又发现了个好玩具酥酥麻麻的，对xnn一般对xyn应该很爽\n#男娘 #伪娘 #女装・男の娘 #萝莉 https://t.co/YEIKldjFMU"
      }
    ],
    "users": [
      {
        "created_at": "2024-04-13T08:25:35.000Z",
        "description": "08年 已有对象",
        "id": "1779063322500874240",
        "name": "困困鱼崽仔小云",
        "profile_image_url": "https://pbs.twimg.com/profile_images/1779145591345324032/MWFxFSnT_normal.jpg",
        "protected": false,
        "public_metrics": {
          "followers_count": 133,
          "following_count": 629,
          "like_count": 10873,
          "listed_count": 0,
          "media_count": 47,
          "tweet_count": 514
        },
        "username": "kunkunyuzaizai",
        "verified": false
      },
      {
        "created_at": "2024-10-29T05:25:19.000Z",
        "description": "重生一代目\n线下先入门槛88+v，聊天，色色",
        "id": "1851133158374457345",
        "location": "苏州",
        "name": "花子あ",
        "pinned_tweet_id": "1900780929498644926",
        "profile_image_url": "https://pbs.twimg.com/profile_images/1887087831425875968/MBdvPX0-_normal.jpg",
        "protected": false,
        "public_metrics": {
          "followers_count": 29959,
          "following_count": 212,
          "like_count": 734,
          "listed_count": 127,
          "media_count": 33,
          "tweet_count": 1048
        },
        "username": "lhy146",
        "verified": false
      }
    ]
  }
}