{
  "data": {
    "article": {},
    "attachments": {},
    "author_id": "1779063322500874240",
    "conversation_id": "2005845952242864152",
    "created_at": "2025-12-30T23:11:57.000Z",
    "edit_controls": {
      "editable_until": "2025-12-31T00:11:57.000Z",
      "edits_remaining": 5,
      "is_edit_eligible": false
    },
    "edit_history_tweet_ids": [
      "2006141236650889364"
    ],
    "entities": {
      "mentions": [
        {
          "end": 15,
          "id": "1814598522895020033",
          "start": 0,
          "username": "LeoTrans112233"
        },
        {
          "end": 29,
          "id": "1667798970700283904",
          "start": 16,
          "username": "Sokei_ko_nya"
        },
        {
          "end": 40,
          "id": "1885154179922227200",
          "start": 30,
          "username": "Snow_Xue_"
        }
      ]
    },
    "geo": {},
    "id": "2006141236650889364",
    "in_reply_to_user_id": "1814598522895020033",
    "lang": "zh",
    "note_tweet": {
      "entities": {}
    },
    "possibly_sensitive": false,
    "public_metrics": {
      "bookmark_count": 0,
      "impression_count": 0,
      "like_count": 0,
      "quote_count": 0,
      "reply_count": 0,
      "retweet_count": 0
    },
    "referenced_tweets": [
      {
        "id": "2005940738518048945",
        "type": "replied_to"
      }
    ],
    "reply_settings": "everyone",
    "text": "@LeoTrans112233 @Sokei_ko_nya @Snow_Xue_ 续航不差吗"
  },
  "includes": {
    "tweets": [
      {
        "article": {},
        "attachments": {},
        "author_id": "1779063322500874240",
        "conversation_id": "2005845952242864152",
        "created_at": "2025-12-30T23:11:57.000Z",
        "edit_controls": {
          "editable_until": "2025-12-31T00:11:57.000Z",
          "edits_remaining": 5,
          "is_edit_eligible": false
        },
        "edit_history_tweet_ids": [
          "2006141236650889364"
        ],
        "entities": {
          "mentions": [
            {
              "end": 15,
              "id": "1814598522895020033",
              "start": 0,
              "username": "LeoTrans112233"
            },
            {
              "end": 29,
              "id": "1667798970700283904",
              "start": 16,
              "username": "Sokei_ko_nya"
            },
            {
              "end": 40,
              "id": "1885154179922227200",
              "start": 30,
              "username": "Snow_Xue_"
            }
          ]
        },
        "geo": {},
        "id": "2006141236650889364",
        "in_reply_to_user_id": "1814598522895020033",
        "lang": "zh",
        "note_tweet": {
          "entities": {}
        },
        "possibly_sensitive": false,
        "public_metrics": {
          "bookmark_count": 0,
          "impression_count": 0,
          "like_count": 0,
          "quote_count": 0,
          "reply_count": 0,
          "retweet_count": 0
        },
        "referenced_tweets": [
          {
            "id": "2005940738518048945",
            "type": "replied_to"
          }
        ],
        "reply_settings": "everyone",
        "text": "@LeoTrans112233 @Sokei_ko_nya @Snow_Xue_ 续航不差吗"
      },
      {
        "article": {},
        "attachments": {},
        "author_id": "1814598522895020033",
        "conversation_id": "2005845952242864152",
        "created_at": "2025-12-30T09:55:15.000Z",
        "edit_controls": {
          "editable_until": "2025-12-30T10:55:15.000Z",
          "edits_remaining": 5,
          "is_edit_eligible": false
        },
        "edit_history_tweet_ids": [
          "2005940738518048945"
        ],
        "entities": {
          "mentions": [
            {
              "end": 13,
              "id": "1667798970700283904",
              "start": 0,
              "username": "Sokei_ko_nya"
            },
            {
              "end": 24,
              "id": "1885154179922227200",
              "start": 14,
              "username": "Snow_Xue_"
            }
          ]
        },
        "geo": {},
        "id": "2005940738518048945",
        "in_reply_to_user_id": "1667798970700283904",
        "lang": "ja",
        "note_tweet": {
          "entities": {}
        },
        "possibly_sensitive": false,
        "public_metrics": {
          "bookmark_count": 0,
          "impression_count": 63,
          "like_count": 1,
          "quote_count": 0,
          "reply_count": 1,
          "retweet_count": 0
        },
        "referenced_tweets": [
          {
            "id": "2005940552693588045",
            "type": "replied_to"
          }
        ],
        "reply_settings": "everyone",
        "text": "@Sokei_ko_nya @Snow_Xue_ SE第三代"
      }
    ],
    "users": [
      {
        "created_at": "2024-04-13T08:25:35.000Z",
        "description": "20080627 INFP 巨蟹男\n168CM/50KG\nXNN\n叫我小云就好了🥰\nDREAM IS BE A GIRL\n\n匿名提问https://t.co/3xGifEiNxg",
        "entities": {
          "description": {
            "urls": [
              {
                "display_url": "ngl.link/kunkunyu627",
                "end": 89,
                "expanded_url": "https://ngl.link/kunkunyu627",
                "start": 66,
                "url": "https://t.co/3xGifEiNxg"
              }
            ]
          }
        },
        "id": "1779063322500874240",
        "name": "困困鱼崽仔小云",
        "pinned_tweet_id": "1961203265527283808",
        "profile_image_url": "https://pbs.twimg.com/profile_images/1907334411152158720/pPb-PHRW_normal.jpg",
        "protected": false,
        "public_metrics": {
          "followers_count": 521,
          "following_count": 2418,
          "like_count": 36801,
          "listed_count": 0,
          "media_count": 153,
          "tweet_count": 2598
        },
        "username": "kunkunyuzaizai",
        "verified": false
      },
      {
        "created_at": "2024-07-20T09:49:54.000Z",
        "description": "简介在置顶喵|无证含糖|HRT起始25.5.5🍥| 08.6.13|高三牲|穷|省吃俭用买糖|求施舍| 是优等生喔|目标是先上大学…| 炸柜…| 不设门槛|同类可直接私我要qq号喔| 非同类要加咱联系方式请先资助一顿饭…… 最喜欢的姐姐兼恋人@KafuAKa0",
        "entities": {
          "description": {
            "mentions": [
              {
                "end": 130,
                "start": 121,
                "username": "KafuAKa0"
              }
            ]
          }
        },
        "id": "1814598522895020033",
        "location": "距离你520m",
        "name": "锦🍥🏳️‍⚧️",
        "pinned_tweet_id": "1986253194083901903",
        "profile_image_url": "https://pbs.twimg.com/profile_images/1998411376675696640/jykyoqnH_normal.jpg",
        "protected": false,
        "public_metrics": {
          "followers_count": 2078,
          "following_count": 426,
          "like_count": 1503,
          "listed_count": 2,
          "media_count": 80,
          "tweet_count": 751
        },
        "username": "LeoTrans112233",
        "verified": false
      },
      {
        "created_at": "2023-06-11T07:41:25.000Z",
        "description": "Rhythm Game player / Bilibili & Youtube uploader / 无证mtf🏳️‍⚧️(25.2.25)/宝宝@RainEngine2024（不建政/No Politics）\n(https://t.co/uTEFVtqHDn)",
        "entities": {
          "description": {
            "mentions": [
              {
                "end": 88,
                "start": 73,
                "username": "RainEngine2024"
              }
            ],
            "urls": [
              {
                "display_url": "youtube.com/@Sokei_ko_nya",
                "end": 130,
                "expanded_url": "https://www.youtube.com/@Sokei_ko_nya",
                "start": 107,
                "url": "https://t.co/uTEFVtqHDn"
              }
            ]
          },
          "url": {
            "urls": [
              {
                "display_url": "space.bilibili.com/298030824",
                "end": 23,
                "expanded_url": "https://space.bilibili.com/298030824",
                "start": 0,
                "url": "https://t.co/8RxAlLpdn7"
              }
            ]
          }
        },
        "id": "1667798970700283904",
        "location": "China mainland",
        "name": "青石巷子喵~🏳️‍⚧️",
        "pinned_tweet_id": "2003481596842979334",
        "profile_image_url": "https://pbs.twimg.com/profile_images/1984276932469600256/m07O6gSV_normal.jpg",
        "protected": false,
        "public_metrics": {
          "followers_count": 489,
          "following_count": 791,
          "like_count": 40304,
          "listed_count": 1,
          "media_count": 215,
          "tweet_count": 1849
        },
        "url": "https://t.co/8RxAlLpdn7",
        "username": "Sokei_ko_nya",
        "verified": false
      },
      {
        "created_at": "2025-01-31T02:32:51.000Z",
        "description": "普通入 | 生产日期2010.3.16 | 无证含糖 |",
        "id": "1885154179922227200",
        "location": "上海 ",
        "name": "雪🍥",
        "profile_image_url": "https://pbs.twimg.com/profile_images/1993960630769094656/zuD-tgtP_normal.jpg",
        "protected": false,
        "public_metrics": {
          "followers_count": 1199,
          "following_count": 1436,
          "like_count": 37438,
          "listed_count": 2,
          "media_count": 484,
          "tweet_count": 3536
        },
        "username": "Snow_Xue_",
        "verified": false
      }
    ]
  }
}