{
  "data": {
    "article": {},
    "attachments": {},
    "author_id": "1779063322500874240",
    "conversation_id": "1933362621849477279",
    "created_at": "2025-06-14T14:57:01.000Z",
    "edit_controls": {
      "editable_until": "2025-06-14T15:57:01.000Z",
      "edits_remaining": 5,
      "is_edit_eligible": false
    },
    "edit_history_tweet_ids": [
      "1933901495981977826"
    ],
    "entities": {
      "mentions": [
        {
          "end": 11,
          "id": "1509391402484080646",
          "start": 0,
          "username": "moran_neko"
        }
      ]
    },
    "geo": {},
    "id": "1933901495981977826",
    "in_reply_to_user_id": "1509391402484080646",
    "lang": "zh",
    "note_tweet": {
      "entities": {}
    },
    "possibly_sensitive": false,
    "public_metrics": {
      "bookmark_count": 0,
      "impression_count": 0,
      "like_count": 0,
      "quote_count": 0,
      "reply_count": 0,
      "retweet_count": 0
    },
    "referenced_tweets": [
      {
        "id": "1933362621849477279",
        "type": "replied_to"
      }
    ],
    "reply_settings": "everyone",
    "text": "@moran_neko 我发现微信8.0.57版本很小"
  },
  "includes": {
    "media": [
      {
        "height": 725,
        "media_key": "3_1933362618082992128",
        "public_metrics": {},
        "type": "photo",
        "url": "https://pbs.twimg.com/media/GtSvDsjbIAAVxMl.jpg",
        "width": 1080
      }
    ],
    "tweets": [
      {
        "article": {},
        "attachments": {},
        "author_id": "1779063322500874240",
        "conversation_id": "1933362621849477279",
        "created_at": "2025-06-14T14:57:01.000Z",
        "edit_controls": {
          "editable_until": "2025-06-14T15:57:01.000Z",
          "edits_remaining": 5,
          "is_edit_eligible": false
        },
        "edit_history_tweet_ids": [
          "1933901495981977826"
        ],
        "entities": {
          "mentions": [
            {
              "end": 11,
              "id": "1509391402484080646",
              "start": 0,
              "username": "moran_neko"
            }
          ]
        },
        "geo": {},
        "id": "1933901495981977826",
        "in_reply_to_user_id": "1509391402484080646",
        "lang": "zh",
        "note_tweet": {
          "entities": {}
        },
        "possibly_sensitive": false,
        "public_metrics": {
          "bookmark_count": 0,
          "impression_count": 0,
          "like_count": 0,
          "quote_count": 0,
          "reply_count": 0,
          "retweet_count": 0
        },
        "referenced_tweets": [
          {
            "id": "1933362621849477279",
            "type": "replied_to"
          }
        ],
        "reply_settings": "everyone",
        "text": "@moran_neko 我发现微信8.0.57版本很小"
      },
      {
        "article": {},
        "attachments": {
          "media_keys": [
            "3_1933362618082992128"
          ]
        },
        "author_id": "1509391402484080646",
        "conversation_id": "1933362621849477279",
        "created_at": "2025-06-13T03:15:43.000Z",
        "edit_controls": {
          "editable_until": "2025-06-13T04:15:43.000Z",
          "edits_remaining": 5,
          "is_edit_eligible": false
        },
        "edit_history_tweet_ids": [
          "1933362621849477279"
        ],
        "entities": {
          "urls": [
            {
              "display_url": "pic.x.com/MScHvAXUoe",
              "end": 28,
              "expanded_url": "https://x.com/moran_neko/status/1933362621849477279/photo/1",
              "media_key": "3_1933362618082992128",
              "start": 5,
              "url": "https://t.co/MScHvAXUoe"
            }
          ]
        },
        "geo": {},
        "id": "1933362621849477279",
        "lang": "zh",
        "note_tweet": {
          "entities": {}
        },
        "possibly_sensitive": false,
        "public_metrics": {
          "bookmark_count": 33,
          "impression_count": 119969,
          "like_count": 808,
          "quote_count": 5,
          "reply_count": 50,
          "retweet_count": 21
        },
        "reply_settings": "everyone",
        "text": "显而易见 https://t.co/MScHvAXUoe"
      }
    ],
    "users": [
      {
        "created_at": "2024-04-13T08:25:35.000Z",
        "description": "20080627",
        "id": "1779063322500874240",
        "name": "困困鱼崽仔小云",
        "pinned_tweet_id": "1914559190288453846",
        "profile_image_url": "https://pbs.twimg.com/profile_images/1907334411152158720/pPb-PHRW_normal.jpg",
        "protected": false,
        "public_metrics": {
          "followers_count": 231,
          "following_count": 1245,
          "like_count": 16918,
          "listed_count": 0,
          "media_count": 83,
          "tweet_count": 910
        },
        "username": "kunkunyuzaizai",
        "verified": false
      },
      {
        "created_at": "2022-03-31T04:45:39.000Z",
        "description": "*尝试找到心中的归属感*\n19♂|日常&碎碎念&发癫&梗图分享|音游|战地1|MC|数码|音乐|🚫不键政|电吉他学习中🎸|懒|主人@_temryava|备用小号@mo5719022066073",
        "entities": {
          "description": {
            "mentions": [
              {
                "end": 75,
                "start": 65,
                "username": "_temryava"
              },
              {
                "end": 96,
                "start": 80,
                "username": "mo5719022066073"
              }
            ]
          },
          "url": {
            "urls": [
              {
                "display_url": "t.me/moran_neko",
                "end": 23,
                "expanded_url": "http://t.me/moran_neko",
                "start": 0,
                "url": "https://t.co/OjtbvqQaRM"
              }
            ]
          }
        },
        "id": "1509391402484080646",
        "location": "空调外机",
        "name": "默然_mo",
        "pinned_tweet_id": "1932361396249079998",
        "profile_image_url": "https://pbs.twimg.com/profile_images/1918685355508932608/QeN0qub6_normal.jpg",
        "protected": false,
        "public_metrics": {
          "followers_count": 1266,
          "following_count": 976,
          "like_count": 12045,
          "listed_count": 3,
          "media_count": 447,
          "tweet_count": 2042
        },
        "url": "https://t.co/OjtbvqQaRM",
        "username": "moran_neko",
        "verified": false
      }
    ]
  }
}